pplotly/Scatter.py
pplotly/__init__.py
pplotly/main.py
pplotly-0.0.4.dist-info/METADATA
pplotly-0.0.4.dist-info/WHEEL
pplotly-0.0.4.dist-info/licenses/LICENSE
pplotly-0.0.4.dist-info/RECORD
