Metadata-Version: 2.3
Name: PPlotly
Version: 0.0.4
Summary: Wrapper project of plotly.py, extra functionalities for scientific plots
Project-URL: Homepage, https://github.com/pkalbhor/pplotly
Project-URL: Issues, https://github.com/pkalbhor/pplotly/issues
Author-email: Pritam Kalbhor <physics.pritam@gmail.com>
Classifier: License :: OSI Approved :: MIT License
Classifier: Operating System :: OS Independent
Classifier: Programming Language :: Python :: 3
Requires-Python: >=3.8
Requires-Dist: plotly>=5.0.0
